{"meta":{"name":"Bell Tree - Stroke","formats":["ogg","m4a"],"baseUrl":"https://danigb.github.io/samples/vcsl/Struck Idiophones/","websfzUrl":"https://danigb.github.io/samples/vcsl/Struck Idiophones/bell-tree-stroke.websfz.json","source":"https://github.com/sgossner/VCSL","license":"Creative Commons 0"},"global":{},"groups":[{"regions":[{"sample":"Bell Tree/Stroke/BellTree_Stroke_1_Mid","pitch_keycenter":60,"lokey":60,"hikey":60,"offset":290,"volume":25},{"sample":"Bell Tree/Stroke/BellTree_Stroke_10_Mid","pitch_keycenter":61,"lokey":61,"hikey":61,"offset":330,"volume":25},{"sample":"Bell Tree/Stroke/BellTree_Stroke_3_Mid","pitch_keycenter":62,"lokey":62,"hikey":62,"offset":290,"volume":25},{"sample":"Bell Tree/Stroke/BellTree_Stroke_4_Mid","pitch_keycenter":63,"lokey":63,"hikey":63,"offset":307,"volume":25}],"ampeg_attack":0,"ampeg_release":15}]}